{"version":1,"entries":{"person_95104_translations":{"at":1774726994268,"data":{"id":95104,"translations":[{"iso_3166_1":"PL","iso_639_1":"pl","name":"Polski","english_name":"Polish","data":{"biography":"W 2001 roku ukończył Akademię Teatralną im. Aleksandra Zelwerowicza w Warszawie (Polska).","name":"Andrzej Andrzejewski","primary":true}},{"iso_3166_1":"KR","iso_639_1":"ko","name":"한국어/조선말","english_name":"Korean","data":{"biography":"","name":"","primary":false}},{"iso_3166_1":"US","iso_639_1":"en","name":"English","english_name":"English","data":{"biography":"","name":"Andrzej Andrzejewski","primary":false}}]}},"person_135202_translations":{"at":1774726995158,"data":{"id":135202,"translations":[{"iso_3166_1":"US","iso_639_1":"en","name":"English","english_name":"English","data":{"biography":"Hajime Inoue (井上 肇, Inōe Hajime, March 29, 1961) is a Japanese actor born in Shinjuku, Tokyo. He belongs to Y.K OFFICE.","name":"Hajime Inoue","primary":false}},{"iso_3166_1":"CN","iso_639_1":"zh","name":"普通话","english_name":"Mandarin","data":{"biography":"井上肇，演员，参演电影《青鸟》、《初秋》、《最近，妹妹的样子有点怪》。","name":"井上肇","primary":false}},{"iso_3166_1":"ES","iso_639_1":"es","name":"Español","english_name":"Spanish","data":{"biography":"Hajime Inoue (井上 肇, Inōe Hajime, 29 de marzo de 1961) es un actor japonés nacido en Shinjuku, Tokio. Pertenece a Y.K OFFICE.","name":"","primary":false}},{"iso_3166_1":"JP","iso_639_1":"ja","name":"日本語","english_name":"Japanese","data":{"biography":"","name":"井上肇","primary":true}},{"iso_3166_1":"DE","iso_639_1":"de","name":"Deutsch","english_name":"German","data":{"biography":"","name":"Hajime Inoue","primary":false}},{"iso_3166_1":"CZ","iso_639_1":"cs","name":"Český","english_name":"Czech","data":{"biography":"","name":"Hadžime Inoue","primary":false}},{"iso_3166_1":"HK","iso_639_1":"zh","name":"普通话","english_name":"Mandarin","data":{"biography":"井上肇，演員，參演電影《青鳥》《初秋》《最近，妹妹的樣子有點怪。》。","name":"井上肇","primary":false}},{"iso_3166_1":"UA","iso_639_1":"uk","name":"Український","english_name":"Ukrainian","data":{"biography":"","name":"Хаджіме Іноуе","primary":false}},{"iso_3166_1":"RU","iso_639_1":"ru","name":"Pусский","english_name":"Russian","data":{"biography":"","name":"Хадзимэ Иноуэ","primary":false}},{"iso_3166_1":"SK","iso_639_1":"sk","name":"Slovenčina","english_name":"Slovak","data":{"biography":"","name":"Hajime Inoue","primary":false}}]}},"person_80823_translations":{"at":1774726995650,"data":{"id":80823,"translations":[{"iso_3166_1":"US","iso_639_1":"en","name":"English","english_name":"English","data":{"biography":"Andrew Morgado is an American voice actor, film writer, ADR mixer and sound editor. He is best known for voicing characters in animated films, animation and video games, such as Cliffjumper in Bumblebee (2018), Sanjar Nandi in The Outer Worlds (2019) and Kouichi Adachi in Yakuza: Like a Dragon (2020).","name":"Andrew Morgado","primary":true}},{"iso_3166_1":"TW","iso_639_1":"zh","name":"普通话","english_name":"Mandarin","data":{"biography":"","name":"","primary":false}},{"iso_3166_1":"CN","iso_639_1":"zh","name":"普通话","english_name":"Mandarin","data":{"biography":"","name":"安德鲁·莫尔加多","primary":false}},{"iso_3166_1":"RU","iso_639_1":"ru","name":"Pусский","english_name":"Russian","data":{"biography":"","name":"Эндрю Моргадо","primary":false}},{"iso_3166_1":"HK","iso_639_1":"zh","name":"普通话","english_name":"Mandarin","data":{"biography":"","name":"安德魯·莫爾加多","primary":false}},{"iso_3166_1":"BY","iso_639_1":"be","name":"беларуская мова","english_name":"Belarusian","data":{"biography":"","name":"Эндру Маргада","primary":false}}]}},"person_7866_translations":{"at":1774727002360,"data":{"id":7866,"translations":[{"iso_3166_1":"US","iso_639_1":"en","name":"English","english_name":"English","data":{"biography":"From Wikipedia, the free encyclopedia\n\nRobert Joseph Pastorelli (June 21, 1954 – March 8, 2004) was an American actor. He had many roles on TV, in movies, and on the stage, including the seven years he played the portly painter Eldin Bernecky on the television series Murphy Brown. His last role was as an oddball hit man in Be Cool, reuniting him with Michael star John Travolta. Pastorelli died of a heroin overdose in 2004.\n\nDescription above from the Wikipedia article Robert Pastorelli, licensed under CC-BY-SA, full list of contributors on Wikipedia.\n\n​","name":"Robert Pastorelli","primary":true}},{"iso_3166_1":"DE","iso_639_1":"de","name":"Deutsch","english_name":"German","data":{"biography":"","name":"","primary":false}},{"iso_3166_1":"CN","iso_639_1":"zh","name":"普通话","english_name":"Mandarin","data":{"biography":"罗伯特·约瑟夫·帕斯托雷利（1954 年 6 月 21 日 - 2004 年 3 月 8 日）是美国演员。","name":"罗伯特·帕斯托雷利","primary":false}},{"iso_3166_1":"UA","iso_639_1":"uk","name":"Український","english_name":"Ukrainian","data":{"biography":"","name":"Роберт Пастореллі","primary":false}},{"iso_3166_1":"HK","iso_639_1":"zh","name":"普通话","english_name":"Mandarin","data":{"biography":"羅伯特·約瑟夫·帕斯託雷利（1954 年 6 月 21 日 - 2004 年 3 月 8 日）是美國演員。","name":"羅伯特·帕斯託雷利","primary":false}}]}},"person_2236383_translations":{"at":1774727014535,"data":{"id":2236383,"translations":[{"iso_3166_1":"US","iso_639_1":"en","name":"English","english_name":"English","data":{"biography":"","name":"Wang Zirui","primary":false}},{"iso_3166_1":"CN","iso_639_1":"zh","name":"普通话","english_name":"Mandarin","data":{"biography":"王子睿，1987年8月29日出生于湖南省长沙市，中国内地男演员，毕业于北京电影学院2008级表演系本科。\n\n2010年，因主演个人首部电视剧《遍地狼烟》而正式出道。2011年2月，主演的年代喜剧电影《家有辣嫂》上映。2012年2月，主演抗日传奇剧《箭在弦上》。2013年3月，主演的年代剧《娘要嫁人》播出。2014年1月，出演的革命剧《利箭纵横》播出。2016年3月，主演的网剧《假如我有超能力》播出；同年，主演年代谍战剧《守旺那小子》。2017年3月，主演都市武侠网络剧《快递先生与贵妃小姐》播出。2020年1月，主演都市职场爱情剧《遇见·璀璨的你》。","name":"王子睿","primary":true}},{"iso_3166_1":"TW","iso_639_1":"zh","name":"普通话","english_name":"Mandarin","data":{"biography":"","name":"Wang Zirui","primary":false}},{"iso_3166_1":"VN","iso_639_1":"vi","name":"Tiếng Việt","english_name":"Vietnamese","data":{"biography":"","name":"Vương Tử Duệ","primary":false}},{"iso_3166_1":"RU","iso_639_1":"ru","name":"Pусский","english_name":"Russian","data":{"biography":"","name":"Ван Цзы Жуй","primary":false}},{"iso_3166_1":"HK","iso_639_1":"zh","name":"普通话","english_name":"Mandarin","data":{"biography":"王子睿，1987 年 8 月 29 日出生於湖南省長沙市，中國內地男演員，畢業於北京電影學院 2008 級表演系本科。\n\n2010 年，因主演個人首部電視劇《遍地狼煙》而正式出道。2011 年 2 月，主演的年代喜劇電影《家有辣嫂》上映。2012 年 2 月，主演抗日傳奇劇《箭在弦上》。2013 年 3 月，主演的年代劇《娘要嫁人》播出。2014 年 1 月，出演的革命劇《利箭縱橫》播出。2016 年 3 月，主演的網劇《假如我有超能力》播出；同年，主演年代諜戰劇《守旺那小子》。2017 年 3 月，主演都市武俠網絡劇《快遞先生與貴妃小姐》播出。2020 年 1 月，主演都市職場愛情劇《遇見·璀璨的你》。","name":"王子睿","primary":false}}]}},"movie_427342_credits":{"at":1774727019677,"data":{"id":427342,"cast":[{"adult":false,"gender":2,"id":1111727,"known_for_department":"Acting","name":"Azamat Nigmanov","original_name":"Азамат Нигманов","popularity":0.6527,"profile_path":"/p4TWRPVf7bUaJKlJQiMxpsWlmmp.jpg","cast_id":4,"character":"Musabek Sengirbaev","credit_id":"5837d4e392514131a101cf6d","order":0},{"adult":false,"gender":2,"id":999734,"known_for_department":"Acting","name":"Alexey Morozov","original_name":"Алексей Морозов","popularity":0.5345,"profile_path":"/svec8wY3Dr5VLfwzQHI7bAy7g3A.jpg","cast_id":5,"character":"Vasiliy Klochkov","credit_id":"5837d5249251414cb9011146","order":1},{"adult":false,"gender":2,"id":583736,"known_for_department":"Acting","name":"Yakiv Kucherevskyi","original_name":"Яків Кучеревський","popularity":0.6239,"profile_path":"/8p7mRTF3DzaRmL0i6rNIcacWRsy.jpg","cast_id":26,"character":"Serzhant Dobrobabin","credit_id":"5c9252bac3a36861075359ca","order":2},{"adult":false,"gender":2,"id":1728202,"known_for_department":"Acting","name":"Oleg Fyodorov","original_name":"Олег Фёдоров","popularity":0.3547,"profile_path":"/4gVlgEYAYMUzatGeEI78MZAaA0B.jpg","cast_id":7,"character":"Grigory Shemyakin, foreman","credit_id":"5861594c92514115cf030ea8","order":3},{"adult":false,"gender":2,"id":1370623,"known_for_department":"Acting","name":"Aleksej Longin","original_name":"Алексей Лонгин","popularity":0.3274,"profile_path":"/1Hh1almUmJEPc1OHVJ0GZ92FuIW.jpg","cast_id":9,"character":"Pavel Gundilovich","credit_id":"586159b9c3a3681a620331df","order":4},{"adult":false,"gender":2,"id":1728203,"known_for_department":"Acting","name":"Dmitriy Girev","original_name":"Дмитрий Гирев","popularity":0.6307,"profile_path":"/cBGvVGWRXgl69A8nemrY69UgjyX.jpg","cast_id":8,"character":"Bondarenko","credit_id":"586159a6c3a3681a680369dc","order":5},{"adult":false,"gender":2,"id":86625,"known_for_department":"Acting","name":"Amadu Mamadakov","original_name":"Амаду Мамадаков","popularity":0.8573,"profile_path":"/rqF1H0GZa8YVUIXLASGOmqI6noU.jpg","cast_id":28,"character":"Alikbay Kosaev","credit_id":"614bcff2326ec1004454c82b","order":6},{"adult":false,"gender":2,"id":1713742,"known_for_department":"Writing","name":"Andrey Shalyopa","original_name":"Андрей Шальопа","popularity":0.2772,"profile_path":"/kezVXeFRkG21puuIFgI3syrM7H.jpg","cast_id":10,"character":"Lieutenant","credit_id":"586159ccc3a3681a7d02e837","order":7},{"adult":false,"gender":2,"id":1825680,"known_for_department":"Acting","name":"Pavel Goncharov","original_name":"Павел Гончаров","popularity":0.289,"profile_path":"/kA1c72GmzeMN2GylXz4mQj3YTPG.jpg","cast_id":18,"character":"Natarov","credit_id":"592c2d87c3a36877df07a4c3","order":8},{"adult":false,"gender":0,"id":1825681,"known_for_department":"Acting","name":"Nikolay Klimchuk","original_name":"Nikolay Klimchuk","popularity":0.0484,"profile_path":null,"cast_id":19,"character":"Petrenko","credit_id":"592c2da7c3a368780a06cb55","order":9},{"adult":false,"gender":2,"id":1745338,"known_for_department":"Acting","name":"Vitaliy Kovalenko","original_name":"Виталий Коваленко","popularity":0.9437,"profile_path":"/lRN20GDsNPVffaJzIGZLankXXvH.jpg","cast_id":20,"character":"Shepetkov","credit_id":"592c2dcd9251413b8a07410c","order":10},{"adult":false,"gender":2,"id":1265314,"known_for_department":"Acting","name":"Aleksandr Plaksin","original_name":"Александр Плаксин","popularity":0.6554,"profile_path":"/a8WTCbk1A9YRfmb7CMDnaVnEXze.jpg","cast_id":22,"character":"Kryuchkov","credit_id":"5a1824e80e0a264cca0143e4","order":11},{"adult":false,"gender":2,"id":1744793,"known_for_department":"Acting","name":"Anton Filipenko","original_name":"Антон Филипенко","popularity":0.9463,"profile_path":"/iBteYzTvGYQk9JCb1SCrQfoWdpf.jpg","cast_id":23,"character":"Timofeev","credit_id":"5aa566de0e0a26075102233c","order":12},{"adult":false,"gender":2,"id":1748447,"known_for_department":"Acting","name":"Anton Kuznetsov","original_name":"Антон Кузнецов","popularity":1.0134,"profile_path":"/bjbf84PeEuIZVPt0nVXXTFLf29S.jpg","cast_id":24,"character":"Fedor Ivanovich Reshetnikov, major, battalion commander","credit_id":"5ab0db540e0a2676db008b35","order":13},{"adult":false,"gender":2,"id":1642335,"known_for_department":"Acting","name":"Sergey Agafonov","original_name":"Сергей Агафонов","popularity":0.324,"profile_path":"/6oQ4usN27UR3hpgF2SwkfKxPbpS.jpg","cast_id":25,"character":"","credit_id":"5ad2b637925141736701ada0","order":14},{"adult":false,"gender":2,"id":84733,"known_for_department":"Acting","name":"Aziz Beyshenaliev","original_name":"Азиз Бейшеналиев","popularity":0.7504,"profile_path":"/7NooA27pTkJwkUdN8fLFrP2Vy7Z.jpg","cast_id":27,"character":"Leitenant Bulatov","credit_id":"60ed01a9b7abb5002a0d65f9","order":15},{"adult":false,"gender":2,"id":1382068,"known_for_department":"Acting","name":"Aleksandr Ustyugov","original_name":"Александр Устюгов","popularity":1.2141,"profile_path":"/wbYiQ5aYKB7xaNugPZ3UvIxxEH7.jpg","cast_id":29,"character":"","credit_id":"616c0140a097dc0065dd9ac4","order":16},{"adult":false,"gender":2,"id":2536245,"known_for_department":"Acting","name":"Dmitriy Murashev","original_name":"Дмитрий Мурашев","popularity":0.5598,"profile_path":"/xWt5JU7loou7Fs5pd6MpDvZu8rV.jpg","cast_id":30,"character":"","credit_id":"62a579d71fd36f0065ddb52a","order":17},{"adult":false,"gender":2,"id":2265020,"known_for_department":"Acting","name":"Andrey Nekrasov","original_name":"Андрей Некрасов","popularity":0.2624,"profile_path":"/mB7oVfg4vYnUcWUNXHDzp55uo5m.jpg","cast_id":31,"character":"","credit_id":"62a57a1705b5494d6eb91616","order":18},{"adult":false,"gender":2,"id":2401876,"known_for_department":"Acting","name":"Aleksey Shutov","original_name":"Алексей Шутов","popularity":0.235,"profile_path":"/7FIMAeUxfmGnw2hNarJbonGelgU.jpg","cast_id":32,"character":"","credit_id":"62a57a24b540020050acc51f","order":19},{"adult":false,"gender":2,"id":2265039,"known_for_department":"Acting","name":"Oleg Senchenko","original_name":"Олег Сенченко","popularity":0.1467,"profile_path":"/tEzegJ0PjYJALey04kGCNzB0p5G.jpg","cast_id":33,"character":"","credit_id":"62a57a3785005d2b176c361e","order":20},{"adult":false,"gender":0,"id":2469674,"known_for_department":"Acting","name":"Andrey Bodrenkov","original_name":"Andrey Bodrenkov","popularity":0.0388,"profile_path":null,"cast_id":34,"character":"","credit_id":"62a57dfc53866e0de1cbb122","order":21},{"adult":false,"gender":0,"id":550739,"known_for_department":"Acting","name":"Lidiya Milyuzina","original_name":"Lidiya Milyuzina","popularity":0.3784,"profile_path":null,"cast_id":35,"character":"","credit_id":"62a57e2c1684f7004f7ae1ad","order":22},{"adult":false,"gender":2,"id":1192059,"known_for_department":"Acting","name":"Dmitriy Sutyrin","original_name":"Дмитрий Сутырин","popularity":0.6511,"profile_path":"/f5lRTTl37ZN0W5vrCDSiuPReOSG.jpg","cast_id":36,"character":"","credit_id":"62a57e41d5569718c6a682f7","order":23},{"adult":false,"gender":0,"id":1665680,"known_for_department":"Acting","name":"Sergey Yatsenyuk","original_name":"Сергей Яценюк","popularity":0.312,"profile_path":"/9SkGT4EQWRcwg6lqfMOfaLl4KVK.jpg","cast_id":37,"character":"","credit_id":"62a57e55e38bd814d30a75b2","order":24},{"adult":false,"gender":2,"id":2221780,"known_for_department":"Acting","name":"Ivan Batarev","original_name":"Иван Батарев","popularity":0.5568,"profile_path":"/et3CZ0mWMuQgLwamjJjEI8jikiU.jpg","cast_id":38,"character":"","credit_id":"62a57e5deb14fa00547510fe","order":25},{"adult":false,"gender":2,"id":2222385,"known_for_department":"Acting","name":"Maksim Belborodov","original_name":"Максим Белбородов","popularity":0.6816,"profile_path":"/iGQqx90Sabc5o9TFgYNDjDC0Rw7.jpg","cast_id":39,"character":"","credit_id":"62a57e6e255dba009b64ffed","order":26},{"adult":false,"gender":2,"id":1961448,"known_for_department":"Acting","name":"Yuriy Golubev","original_name":"Юрий Голубев","popularity":0.2188,"profile_path":"/kaTlS2UONCLD7NkcGxBg599PaJq.jpg","cast_id":40,"character":"","credit_id":"62a57e83d5dbc20066aa7cf8","order":27},{"adult":false,"gender":0,"id":2265055,"known_for_department":"Acting","name":"Nikolay Kiy","original_name":"Nikolay Kiy","popularity":0.1359,"profile_path":null,"cast_id":41,"character":"","credit_id":"62a57e8b53866e0de0f2dc58","order":28},{"adult":false,"gender":0,"id":2265044,"known_for_department":"Acting","name":"Mikhail Dernov","original_name":"Mikhail Dernov","popularity":0.0775,"profile_path":null,"cast_id":42,"character":"","credit_id":"62a57e9ad5569718c7527a6c","order":29},{"adult":false,"gender":2,"id":2269322,"known_for_department":"Acting","name":"Nikolay Klyamchuk","original_name":"Николай Клямчук","popularity":0.2318,"profile_path":"/aF3NWTnB2s4XI6wWz18Cnl9VVTR.jpg","cast_id":43,"character":"","credit_id":"62a57ebd8efe7300a593ae7b","order":30},{"adult":false,"gender":0,"id":2218002,"known_for_department":"Acting","name":"Alexey Aleshkin","original_name":"Alexey Aleshkin","popularity":0.1491,"profile_path":null,"cast_id":44,"character":"","credit_id":"62a57f31d5dbc20066aa7e43","order":31},{"adult":false,"gender":2,"id":2358942,"known_for_department":"Acting","name":"Vitaly Khadzhiev","original_name":"Vitaly Khadzhiev","popularity":0.0797,"profile_path":"/zLRvKFIqCuvk0Go625ymj5x5Yh3.jpg","cast_id":45,"character":"","credit_id":"62a57f4d05b5494d6fea277a","order":32},{"adult":false,"gender":2,"id":2217020,"known_for_department":"Acting","name":"Vasily Mitkin","original_name":"Vasily Mitkin","popularity":0.0828,"profile_path":"/cXVeO2MP8pVwSpjyyLNukq1F4QM.jpg","cast_id":46,"character":"","credit_id":"62a57f5f4c1d9a0066fa77f8","order":33},{"adult":false,"gender":2,"id":2216143,"known_for_department":"Acting","name":"Sergey Korenkov","original_name":"Сергей Кореньков","popularity":0.2795,"profile_path":"/hghVf5Up3XknPibPAovfHruV3c9.jpg","cast_id":47,"character":"","credit_id":"62a57f78255dba004f3239a2","order":34},{"adult":false,"gender":2,"id":2022885,"known_for_department":"Acting","name":"Aleksandr Kovalyov","original_name":"Александр Ковалёв","popularity":0.4578,"profile_path":"/nWXU7YKwBTdlHl22rwwHhRsSUll.jpg","cast_id":51,"character":"","credit_id":"669163b38e48cb01d39e27c0","order":35}],"crew":[{"adult":false,"gender":1,"id":4486134,"known_for_department":"Sound","name":"Polina Volynkina","original_name":"Полина Волынкина","popularity":0.1221,"profile_path":null,"credit_id":"65a80bfcaa789801316295ba","department":"Sound","job":"Sound Director"},{"adult":false,"gender":1,"id":3152448,"known_for_department":"Costume & Make-Up","name":"Viktoriya Igumnova","original_name":"Виктория Игумнова","popularity":0.2694,"profile_path":null,"credit_id":"65a80c1d5b9508012fbf3a05","department":"Costume & Make-Up","job":"Costume Design"},{"adult":false,"gender":0,"id":2533409,"known_for_department":"Crew","name":"Maksim Dragoy","original_name":"Maksim Dragoy","popularity":0.2759,"profile_path":null,"credit_id":"65a80c7d1bf8760129c9c21d","department":"Crew","job":"Stunt Coordinator"},{"adult":false,"gender":2,"id":1713741,"known_for_department":"Directing","name":"Kim Druzhinin","original_name":"Ким Дружинин","popularity":0.4924,"profile_path":"/iXh2sjtKWB6SYTcxeaj2ujadS47.jpg","credit_id":"5837d4a2c3a36836b301f24a","department":"Directing","job":"Director"},{"adult":false,"gender":2,"id":1713742,"known_for_department":"Writing","name":"Andrey Shalyopa","original_name":"Андрей Шальопа","popularity":0.2772,"profile_path":"/kezVXeFRkG21puuIFgI3syrM7H.jpg","credit_id":"5837d4afc3a36836ae01cc41","department":"Directing","job":"Director"},{"adult":false,"gender":2,"id":1713742,"known_for_department":"Writing","name":"Andrey Shalyopa","original_name":"Андрей Шальопа","popularity":0.2772,"profile_path":"/kezVXeFRkG21puuIFgI3syrM7H.jpg","credit_id":"5861590c9251414e3a00c87f","department":"Writing","job":"Writer"},{"adult":false,"gender":0,"id":1825674,"known_for_department":"Production","name":"Anton Yudintsev","original_name":"Anton Yudintsev","popularity":0.0473,"profile_path":null,"credit_id":"592c2c7b9251413b4a075735","department":"Production","job":"Producer"},{"adult":false,"gender":2,"id":1825675,"known_for_department":"Sound","name":"Mikhail Kostylev","original_name":"Михаил Костылев","popularity":0.0663,"profile_path":"/50z1Fvyq5RMEd2AGmQizHxjgr3u.jpg","credit_id":"592c2c8bc3a36877bc07ec8a","department":"Sound","job":"Music"},{"adult":false,"gender":2,"id":1825676,"known_for_department":"Camera","name":"Nikita Rozhdestvenskiy","original_name":"Никита Рождественский","popularity":0.1158,"profile_path":"/wz5OOKxaDIVrTcbzajzBsm8Bj8Z.jpg","credit_id":"592c2c9bc3a36877ee077e64","department":"Camera","job":"Director of Photography"},{"adult":false,"gender":0,"id":1825677,"known_for_department":"Editing","name":"Vitaly Vinogradov","original_name":"Vitaly Vinogradov","popularity":0.1757,"profile_path":"/9S18I2nc8XxzSWwuGigJJuXQ1aA.jpg","credit_id":"592c2cadc3a36877bc07ecaf","department":"Editing","job":"Editor"},{"adult":false,"gender":1,"id":1401613,"known_for_department":"Production","name":"Marina Leonova","original_name":"Marina Leonova","popularity":0.1745,"profile_path":null,"credit_id":"592c2cc29251413b500733a9","department":"Production","job":"Casting"},{"adult":false,"gender":1,"id":1825678,"known_for_department":"Art","name":"Ekaterina Lizogubova","original_name":"Ekaterina Lizogubova","popularity":0.0338,"profile_path":null,"credit_id":"592c2cd39251413b8a074058","department":"Art","job":"Production Design"},{"adult":false,"gender":0,"id":1825679,"known_for_department":"Visual Effects","name":"Igor Eyt","original_name":"Igor Eyt","popularity":0.1172,"profile_path":null,"credit_id":"592c2cedc3a36877fd067391","department":"Visual Effects","job":"Special Effects Supervisor"}]}},"movie_526034_keywords":{"at":1774727019902,"data":{"id":526034,"keywords":[{"id":2231,"name":"drug dealer"},{"id":1862,"name":"coming out"},{"id":65,"name":"holiday"},{"id":2316,"name":"women's sexual identity"},{"id":2669,"name":"motel"},{"id":4543,"name":"thanksgiving"},{"id":10201,"name":"death of father"},{"id":9833,"name":"lesbian relationship"},{"id":158718,"name":"lgbt"},{"id":182657,"name":"family gathering"},{"id":187056,"name":"woman director"},{"id":226766,"name":"roommate issues"},{"id":242454,"name":"former lovers"}]}},"person_2038734_translations":{"at":1774727022861,"data":{"id":2038734,"translations":[{"iso_3166_1":"RU","iso_639_1":"ru","name":"Pусский","english_name":"Russian","data":{"biography":"","name":"Николай Горшков","primary":true}},{"iso_3166_1":"US","iso_639_1":"en","name":"English","english_name":"English","data":{"biography":"","name":"Nikolay Gorshkov","primary":false}}]}},"person_2121690_translations":{"at":1774727156117,"data":{"id":2121690,"translations":[{"iso_3166_1":"US","iso_639_1":"en","name":"English","english_name":"English","data":{"biography":"Teng Xin, a voice actor, graduated from Sichuan Conservatory of Music. He entered Beijing dubbing circle in 2008.","name":"Teng Xin","primary":false}},{"iso_3166_1":"TW","iso_639_1":"zh","name":"普通话","english_name":"Mandarin","data":{"biography":"","name":"藤新","primary":false}},{"iso_3166_1":"RU","iso_639_1":"ru","name":"Pусский","english_name":"Russian","data":{"biography":"Тэн Синь, актер озвучивания, окончил Сычуаньскую консерваторию По классу музыки. В 2008 году поступил в пекинскую студию дубляжа.","name":"Тэн Синь","primary":false}},{"iso_3166_1":"CN","iso_639_1":"zh","name":"普通话","english_name":"Mandarin","data":{"biography":"藤新，本名崔健文，艺名藤新，1987年7月2日出生于辽宁大连，中国配音演员，毕业于四川音乐学院，08年进入北京配音圈。探索频道DISCOVERY配音演员、VOASIA、怀旧配音联盟(网络社团) 、声创联盟中文配音社团(网络社团)成员。\n\n曾为《尸兄》《一人之下》《十万个冷笑话》《疯狂动物城》《全职高手》《摩尔庄园》等作品进行配音。2020年，执导动画《妖精种植手册》。\n\n2012年，其作品《摩尔庄园》被提名为第18届动画类“白玉兰”奖候选作品。","name":"藤新","primary":false}},{"iso_3166_1":"HK","iso_639_1":"zh","name":"普通话","english_name":"Mandarin","data":{"biography":"藤新，本名崔健文，藝名藤新，1987 年 7 月 2 日出生於遼寧大聯，中國配音演員，畢業於四川音樂學院，08 年進入北京配音圈。探索頻道 DISCOVERY 配音演員、VOASIA、懷舊配音聯盟 (網絡社團) 、聲創聯盟中文配音社團 (網絡社團) 成員。\n\n曾為《屍兄》《一人之下》《十萬個冷笑話》《優獸大都會》《全職高手》《摩爾莊園》等作品進行配音。2020 年，執導動畫《妖精種植手冊》。\n\n2012 年，其作品《摩爾莊園》被提名為第 18 屆動畫類“白玉蘭”獎候選作品。","name":"藤新","primary":false}}]}}}}