{"69e211ba748ca16f085e500b":{"id":"69e211ba748ca16f085e500b","tmdb":{"type":"tv","id":"278868","season":1,"vote_average":4.8,"vote_count":2},"imdb":null,"cast":["Hứa Khải","Đinh Dũng Đại","Đặng Ân Hy","Hu Ke","Đồ Tùng Nham","Qu Shanshan","Zhao Qi","Hà Phụng Thiên","Su Xin"],"director":["裘仲维"],"cast_meta":[{"name":"Hứa Khải","name_vi":"Hứa Khải","name_original":"Xu Kai","tmdb_id":2091759,"profile":"https://image.tmdb.org/t/p/w500/wEfatQWa3v9tNtmgr5LOOmFSSJj.jpg","tmdb_url":"https://www.themoviedb.org/person/2091759"},{"name":"Đinh Dũng Đại","name_vi":"Đinh Dũng Đại","name_original":"Ding Yongdai","tmdb_id":1194773,"profile":"https://image.tmdb.org/t/p/w500/hB1xrY9K0jwhWsbLEbsJl55h98T.jpg","tmdb_url":"https://www.themoviedb.org/person/1194773"},{"name":"Đặng Ân Hy","name_vi":"Đặng Ân Hy","name_original":"Deng Enxi","tmdb_id":1780718,"profile":"https://image.tmdb.org/t/p/w500/mljbAriACCCSNYAe6bDMiCFgViu.jpg","tmdb_url":"https://www.themoviedb.org/person/1780718"},{"name":"Hu Ke","name_vi":null,"name_original":"Hu Ke","tmdb_id":544790,"profile":"https://image.tmdb.org/t/p/w500/3LMCJlrifOO1Me47sjeQ3xAu22o.jpg","tmdb_url":"https://www.themoviedb.org/person/544790"},{"name":"Đồ Tùng Nham","name_vi":"Đồ Tùng Nham","name_original":"Tu Songyan","tmdb_id":2276453,"profile":"https://image.tmdb.org/t/p/w500/xMN5dqyJQUFgQWp2GUheeBWpXGp.jpg","tmdb_url":"https://www.themoviedb.org/person/2276453"},{"name":"Qu Shanshan","name_vi":null,"name_original":"Qu Shanshan","tmdb_id":2795038,"profile":"https://image.tmdb.org/t/p/w500/q9SYzyqWl35bSDsL2DJ02l9GfHz.jpg","tmdb_url":"https://www.themoviedb.org/person/2795038"},{"name":"Zhao Qi","name_vi":null,"name_original":"Zhao Qi","tmdb_id":64990,"profile":"https://image.tmdb.org/t/p/w500/zjZKAotAcOjiCpRXL2MRFFFY8DW.jpg","tmdb_url":"https://www.themoviedb.org/person/64990"},{"name":"Hà Phụng Thiên","name_vi":"Hà Phụng Thiên","name_original":"He Fengtian","tmdb_id":3093293,"profile":"https://image.tmdb.org/t/p/w500/7FkFjxRmaOiYvkwZw5AXbFQ702.jpg","tmdb_url":"https://www.themoviedb.org/person/3093293"},{"name":"Su Xin","name_vi":null,"name_original":"Su Xin","tmdb_id":2181656,"profile":"https://image.tmdb.org/t/p/w500/lqCsXTe3B9PnL6NtrWBd1xhPgE7.jpg","tmdb_url":"https://www.themoviedb.org/person/2181656"}],"keywords":[],"tmdb_checked":true}}